neural_condense/__init__.py
neural_condense/client.py
neural_condense/constants.py
neural_condense/datatypes.py
neural_condense-0.0.6.dist-info/METADATA
neural_condense-0.0.6.dist-info/WHEEL
neural_condense-0.0.6.dist-info/top_level.txt
neural_condense-0.0.6.dist-info/RECORD
