Metadata-Version: 2.1
Name: neural_condense
Version: 0.0.6
Summary: Wrapped API for Neural Condense Subnet - Bittensor
Home-page: https://github.com/condenses/neural-condense
Author: CondenseAI
Author-email: 
Classifier: Programming Language :: Python :: 3
Classifier: License :: OSI Approved :: MIT License
Classifier: Operating System :: OS Independent
Requires-Python: >=3.8
Requires-Dist: httpx
Requires-Dist: numpy <2
Requires-Dist: pydantic
